dsram/__init__.py
dsram/likelihood.py
dsram/severity.py
dsram-1.0.5.dist-info/LICENSE
dsram-1.0.5.dist-info/METADATA
dsram-1.0.5.dist-info/WHEEL
dsram-1.0.5.dist-info/top_level.txt
dsram-1.0.5.dist-info/RECORD
