Metadata-Version: 2.1
Name: dsram
Version: 1.0.5
Summary: A quantitative cyber risk management calculator
Home-page: https://github.com/Deploying-Securely/DSRAM
Author: Walter Haydock
Author-email: walter@deploy-securely.com
Classifier: License :: OSI Approved :: Apache Software License
License-File: LICENSE
